{"version":1,"resource":"file:///home/elmaikina/Code/arc-black-theme/common/cinnamon/4.2/sass/_colors.scss","entries":[{"id":"vdSi.scss","source":"searchReplace.source","timestamp":1746777740888},{"id":"8j8i.scss","source":"searchReplace.source","timestamp":1746777867622},{"id":"aBCF.scss","source":"searchReplace.source","timestamp":1746777991152},{"id":"tJjI.scss","source":"searchReplace.source","timestamp":1746778030296},{"id":"tD1E.scss","source":"searchReplace.source","timestamp":1746778040721},{"id":"cr8E.scss","source":"searchReplace.source","timestamp":1746778052517},{"id":"ZvPI.scss","source":"searchReplace.source","timestamp":1746778063794}]}